bro_pkg-2.5.0.data/scripts/bro-pkg
bro_pkg-2.5.0.data/scripts/zkg
bropkg/__init__.py
bropkg/_util.py
bropkg/manager.py
bropkg/package.py
bropkg/source.py
zeekpkg/__init__.py
zeekpkg/_util.py
zeekpkg/manager.py
zeekpkg/package.py
zeekpkg/source.py
bro_pkg-2.5.0.dist-info/COPYING
bro_pkg-2.5.0.dist-info/METADATA
bro_pkg-2.5.0.dist-info/WHEEL
bro_pkg-2.5.0.dist-info/top_level.txt
bro_pkg-2.5.0.dist-info/RECORD
