Metadata-Version: 2.1
Name: bro-pkg
Version: 2.5.0
Summary: The Zeek Package Manager
Home-page: https://github.com/zeek/package-manager
Maintainer: The Zeek Project
Maintainer-email: info@zeek.org
License: University of Illinois/NCSA Open Source License
Keywords: zeek bro zeekctl zeekcontrol broctl brocontrol package manager scripts plugins security
Platform: UNKNOWN
Classifier: Development Status :: 5 - Production/Stable
Classifier: Environment :: Console
Classifier: License :: OSI Approved :: University of Illinois/NCSA Open Source License
Classifier: Operating System :: POSIX :: Linux
Classifier: Operating System :: MacOS :: MacOS X
Classifier: Programming Language :: Python :: 3
Classifier: Topic :: System :: Networking :: Monitoring
Classifier: Topic :: Utilities
Requires-Dist: btest
Requires-Dist: gitpython
Requires-Dist: semantic-version
